scriptonite/__init__.py
scriptonite/configuration.py
scriptonite/email.py
scriptonite/logging.py
scriptonite/notify/__init__.py
scriptonite/notify/base.py
scriptonite/notify/email.py
scriptonite/notify/pushover.py
scriptonite/notify/slack.py
scriptonite/utilities.py
scriptonite-1.0.3.dist-info/METADATA
scriptonite-1.0.3.dist-info/WHEEL
scriptonite-1.0.3.dist-info/RECORD
