Metadata-Version: 2.1
Name: scriptonite
Version: 1.0.3
Summary: A toolkit for scripting in Python
License: GPL-3.0-or-later
Author: Andrea Mistrali
Author-email: andrea@mistrali.pw
Maintainer: Andrea Mistrali
Maintainer-email: andrea@mistrali.pw
Requires-Python: >=3.10,<4.0
Classifier: License :: OSI Approved :: GNU General Public License v3 or later (GPLv3+)
Classifier: Programming Language :: Python :: 3
Classifier: Programming Language :: Python :: 3.10
Classifier: Programming Language :: Python :: 3.11
Classifier: Programming Language :: Python :: 3.12
